MANIFEST.in
setup.py
Cessa.egg-info/PKG-INFO
Cessa.egg-info/SOURCES.txt
Cessa.egg-info/dependency_links.txt
Cessa.egg-info/top_level.txt
cessa/__init__.py
cessa/audit.py
cessa/config.py
cessa/docker.py
cessa/knowledge.py
cessa/profile.py
cessa/rule.py
cessa/trace.py
cessa/expert/__init__.py
cessa/expert/setup.py
cessa/expert/compiled_krb/__init__.py
cessa/expert/compiled_krb/argument.fbc
cessa/expert/compiled_krb/bc_relate_bc.py
cessa/expert/compiled_krb/compiled_pyke_files.py
cessa/expert/compiled_krb/macro.fbc
cessa/expert/compiled_krb/question_fact.fbc
cessa/expert/compiled_krb/question_rule_bc.py
cessa/expert/compiled_krb/questions.qbc
cessa/expert/compiled_krb/syscall.fbc
client/cessa
configs/clabel.list
configs/sysdig.json
configs/systable.list
pyke/__init__.py
pyke/ask_tty.py
pyke/ask_wx.py
pyke/bc_rule.py
pyke/condensedPrint.py
pyke/contexts.py
pyke/fact_base.py
pyke/fc_rule.py
pyke/goal.py
pyke/immutable_dict.py
pyke/knowledge_base.py
pyke/knowledge_engine.py
pyke/krb_traceback.py
pyke/pattern.py
pyke/qa_helpers.py
pyke/question_base.py
pyke/rule_base.py
pyke/special.py
pyke/target_pkg.py
pyke/test.py
pyke/unique.py
pyke/user_question.py
pyke/krb_compiler/__init__.py
pyke/krb_compiler/compiler_bc.py
pyke/krb_compiler/helpers.py
pyke/krb_compiler/kfbparser.py
pyke/krb_compiler/kfbparser_tables.py
pyke/krb_compiler/kqb_parser.py
pyke/krb_compiler/krbparser.py
pyke/krb_compiler/krbparser_tables.py
pyke/krb_compiler/scanner.py
pyke/krb_compiler/scanner_tables.py
pyke/krb_compiler/ply/__init__.py
pyke/krb_compiler/ply/lex.py
pyke/krb_compiler/ply/yacc.py