Metadata-Version: 1.1
Name: Cessa
Version: 1.2.5rc1
Summary: A Docker security reinforcement system based on system call interception
Home-page: https://github.com/ihac/cessa
Author: Xiao An
Author-email: hac@zju.edu.cn
License: MIT
Keywords: Docker container,security
Platform: UNKNOWN
Classifier: Development Status :: 4 - Beta
Classifier: Programming Language :: Python :: 3 :: Only
Classifier: Programming Language :: Python :: 3
Classifier: Programming Language :: Python :: 3.4
Classifier: Programming Language :: Python :: 3.5
Classifier: Programming Language :: Python :: 3.6
